{
  "params" : [
    {
      "type" : "float",
      "base" : {
        "label" : "Oxygen Mass",
        "value" : 0.64999997615814209,
        "min" : 0,
        "controlType" : "inputfield",
        "max" : 1
      }
    },
    {
      "type" : "float",
      "base" : {
        "label" : "Carbon Mass",
        "value" : 0.18500000238418579,
        "min" : 0,
        "controlType" : "inputfield",
        "max" : 1
      }
    },
    {
      "type" : "float",
      "base" : {
        "label" : "Hydrogen Mass",
        "value" : 0.094999998807907104,
        "min" : 0,
        "controlType" : "inputfield",
        "max" : 1
      }
    },
    {
      "type" : "float",
      "base" : {
        "label" : "Nitrogen Mass",
        "value" : 0.032000001519918442,
        "min" : 0,
        "controlType" : "inputfield",
        "max" : 1
      }
    },
    {
      "type" : "float",
      "base" : {
        "label" : "Calcium Mass",
        "value" : 0.014999999664723873,
        "min" : 0,
        "controlType" : "inputfield",
        "max" : 1
      }
    },
    {
      "type" : "float",
      "base" : {
        "label" : "Phosphorus Mass",
        "value" : 0.0099999997764825821,
        "min" : 0,
        "controlType" : "inputfield",
        "max" : 1
      }
    },
    {
      "type" : "float",
      "base" : {
        "label" : "Potassium Mass",
        "value" : 0.0040000001899898052,
        "min" : 0,
        "controlType" : "inputfield",
        "max" : 1
      }
    },
    {
      "type" : "float",
      "base" : {
        "label" : "Sulfur Mass",
        "value" : 0.0030000000260770321,
        "min" : 0,
        "controlType" : "inputfield",
        "max" : 1
      }
    },
    {
      "type" : "float",
      "base" : {
        "label" : "Sodium Mass",
        "value" : 0.0020000000949949026,
        "min" : 0,
        "controlType" : "inputfield",
        "max" : 1
      }
    },
    {
      "type" : "float",
      "base" : {
        "label" : "Chlorine Mass",
        "value" : 0.0020000000949949026,
        "min" : 0,
        "controlType" : "inputfield",
        "max" : 1
      }
    },
    {
      "type" : "float",
      "base" : {
        "label" : "Magnesium Mass",
        "value" : 0.0010000000474974513,
        "min" : 0,
        "controlType" : "inputfield",
        "max" : 1
      }
    },
    {
      "type" : "float",
      "base" : {
        "label" : "Iron Mass",
        "value" : 5.9999996437909431e-07,
        "min" : 0,
        "controlType" : "inputfield",
        "max" : 1
      }
    },
    {
      "type" : "float",
      "base" : {
        "label" : "Fluorine Mass",
        "value" : 3.700000092976552e-07,
        "min" : 0,
        "controlType" : "inputfield",
        "max" : 1
      }
    },
    {
      "type" : "float",
      "base" : {
        "label" : "Zinc Mass",
        "value" : 3.1999999805520929e-07,
        "min" : 0,
        "controlType" : "inputfield",
        "max" : 1
      }
    },
    {
      "type" : "float",
      "base" : {
        "label" : "Silicon Mass",
        "value" : 1.9999998812636477e-07,
        "min" : 0,
        "controlType" : "inputfield",
        "max" : 1
      }
    },
    {
      "type" : "float",
      "base" : {
        "label" : "Gallium Mass",
        "value" : 4.90000005015645e-08,
        "min" : 0,
        "controlType" : "inputfield",
        "max" : 1
      }
    },
    {
      "type" : "float",
      "base" : {
        "label" : "Rubidium Mass",
        "value" : 4.6000000253343387e-08,
        "min" : 0,
        "controlType" : "inputfield",
        "max" : 1
      }
    },
    {
      "type" : "float",
      "base" : {
        "label" : "Strontium Mass",
        "value" : 4.6000000253343387e-08,
        "min" : 0,
        "controlType" : "inputfield",
        "max" : 1
      }
    },
    {
      "type" : "float",
      "base" : {
        "label" : "Bromine Mass",
        "value" : 2.900000062311392e-08,
        "min" : 0,
        "controlType" : "inputfield",
        "max" : 1
      }
    },
    {
      "type" : "float",
      "base" : {
        "label" : "Lead Mass",
        "value" : 1.6999999630229468e-08,
        "min" : 0,
        "controlType" : "inputfield",
        "max" : 1
      }
    },
    {
      "type" : "float",
      "base" : {
        "label" : "Copper Mass",
        "value" : 7.2000000272964826e-07,
        "min" : 0,
        "controlType" : "inputfield",
        "max" : 1
      }
    }
  ]
}